{"value": {"ticker": "HAVELLS.NS", "source": "yahoo", "current_price": 1294.3, "market_cap": 811906236416, "pe_ratio": 54.727276, "pb_ratio": 9.355258, "beta": 0.146, "eps": 23.65, "book_value": 138.35, "dividend_yield": 0.74, "sector": "Industrials", "industry": "Electrical Equipment & Parts", "week_52_high": 1673.8, "week_52_low": 1250.1, "avg_volume": 798474, "revenue_ttm": 223661293568, "net_income_ttm": 14853300224, "ebitda_ttm": 21554774016, "gross_margin": 0.32847, "operating_margin": 0.072919995, "profit_margin": 0.06641, "debt_to_equity": 3.292, "earnings_growth": 0.081, "revenue_growth": 0.143, "shares_outstanding": 627256842, "annual_revenue": {"2025-03-31": 216000800000.0, "2024-03-31": 184733100000.0, "2023-03-31": 168057200000.0, "2022-03-31": 138354500000.0}, "annual_net_income": {"2025-03-31": 14722600000.0, "2024-03-31": 12707600000.0, "2023-03-31": 10717300000.0, "2022-03-31": 11964700000.0}, "annual_ebitda": {"2025-03-31": 24341300000.0, "2024-03-31": 20915800000.0, "2023-03-31": 17768500000.0, "2022-03-31": 19208600000.0}, "annual_gross_profit": {"2025-03-31": 64606200000.0, "2024-03-31": 54669400000.0, "2023-03-31": 47136200000.0, "2022-03-31": 40792900000.0}, "annual_operating_income": {"2025-03-31": 18323200000.0, "2024-03-31": 15692900000.0, "2023-03-31": 13453400000.0, "2022-03-31": 15331200000.0}, "total_assets": 138094100000.0, "total_liabilities": 54684400000.0, "stockholders_equity": 83237900000.0, "cash": 8063000000.0, "total_debt": 3185400000.0, "current_assets": 88705100000.0, "current_liabilities": 47747600000.0, "annual_operating_cashflow": {"2025-03-31": 15152900000.0, "2024-03-31": 19528900000.0, "2023-03-31": 5649400000.0, "2022-03-31": 17280200000.0}, "annual_capex": {"2025-03-31": -7659500000.0, "2024-03-31": -7860700000.0, "2023-03-31": -5877900000.0, "2022-03-31": -2583200000.0}, "annual_free_cashflow": {"2025-03-31": 7493400000.0, "2024-03-31": 11668200000.0, "2023-03-31": -228500000.0, "2022-03-31": 14697000000.0}, "price_return_1y": -10.65, "price_return_3y": 11.63, "price_return_5y": 28.69, "market_cap_bucket": "large", "data_quality": 0.5, "symbol": "HAVELLS", "exchange": "BOTH", "company_name": "", "revenue_cagr_1y": null, "revenue_cagr_3y": null, "revenue_cagr_5y": null, "revenue_cagr_10y": null, "profit_cagr_1y": null, "profit_cagr_3y": null, "profit_cagr_5y": null, "profit_cagr_10y": null, "eps_cagr_3y": null, "eps_cagr_5y": null, "roe": null, "roce": null, "roa": null, "opm": null, "npm": null, "ebitda_margin": null, "opm_trend": null, "npm_trend": null, "current_ratio": null, "interest_coverage": null, "debt_reduction_trend": false, "cash_to_debt_ratio": 2.5312362654611666, "cfo_to_profit_ratio": null, "fcf_crore": null, "fcf_yield": null, "fcf_cagr_3y": null, "cash_conversion_cycle": null, "ev_ebitda": null, "ps_ratio": null, "earnings_yield": 1.827242415646633, "peg_ratio": null, "profit_consistency_score": null, "roe_consistency": null, "margin_stability": null, "earnings_predictability": null, "years_of_positive_growth": 0, "asset_turnover": 0.0, "inventory_turnover": null, "receivables_days": null, "capex_to_revenue": null, "working_capital_intensity": null, "red_flags": ["Rising debt (D/E > 2)"], "strengths": [], "quality_score": 0.0, "growth_score": 0.0, "valuation_score": 30.07, "financial_health_score": 32.08, "consistency_score": 50.0, "overall_score": 15.83, "verdict": "AVOID", "confidence": 23.08, "intent": null, "weights_applied": {"quality": 0.3, "growth": 0.25, "valuation": 0.2, "financial_health": 0.15, "consistency": 0.1}, "score_breakdown": {"quality": {"roce": null, "roce_score": null, "roe": null, "roe_score": null, "opm": null, "opm_score": null}, "growth": {"revenue_cagr_5y": null, "revenue_score": null, "profit_cagr_5y": null, "profit_score": null, "eps_cagr_5y": null, "eps_score": null}, "valuation": {"pe_ratio": 54.727276, "pe_score": 30.136362, "pb_ratio": 9.355258, "pb_score": 30.0}, "financial_health": {"debt_to_equity": 3.292, "de_score": 32.08, "current_ratio": null, "cr_score": null, "interest_coverage": null, "ic_score": null, "cfo_to_profit_ratio": null, "cfo_score": null}, "consistency": {"profit_consistency_score": null, "pc_score": null, "roe_consistency_std": null, "roe_consistency_score": null, "margin_stability_std": null, "margin_stability_score": null}}, "analysis": {"symbol": "HAVELLS", "company_name": "", "revenue_cagr_1y": null, "revenue_cagr_3y": null, "revenue_cagr_5y": null, "revenue_cagr_10y": null, "profit_cagr_1y": null, "profit_cagr_3y": null, "profit_cagr_5y": null, "profit_cagr_10y": null, "eps_cagr_3y": null, "eps_cagr_5y": null, "roe": null, "roce": null, "roa": null, "opm": null, "npm": null, "ebitda_margin": null, "gross_margin": null, "opm_trend": null, "npm_trend": null, "debt_to_equity": 3.292, "current_ratio": null, "interest_coverage": null, "debt_reduction_trend": false, "cash_to_debt_ratio": 2.5312362654611666, "cfo_to_profit_ratio": null, "fcf_crore": null, "fcf_yield": null, "fcf_cagr_3y": null, "cash_conversion_cycle": null, "pe_ratio": 54.727276, "pb_ratio": 9.355258, "ev_ebitda": null, "ps_ratio": null, "earnings_yield": 1.827242415646633, "peg_ratio": null, "profit_consistency_score": null, "roe_consistency": null, "margin_stability": null, "earnings_predictability": null, "years_of_positive_growth": 0, "asset_turnover": 0.0, "inventory_turnover": null, "receivables_days": null, "capex_to_revenue": null, "working_capital_intensity": null, "price_return_1y": -10.65, "price_return_3y": 11.63, "price_return_5y": 28.69, "red_flags": ["Rising debt (D/E > 2)"], "strengths": []}, "valuation": {"scenarios": {}, "average_intrinsic_value": null, "valuation_range": {}, "current_price": 0.0, "overall_margin_of_safety": null, "verdict": "N/A", "confidence": 0.5, "methods_used": [], "reasoning": "Valuation based on 0 method(s): . Confidence score: 50.0% (moderate confidence)."}}, "expires_at": 1773962680.7039282, "ttl_hours": 6}